_cmultifib.c
setup.cfg
setup.py
multifib/__init__.py
multifib/iterative.py
multifib/recursive.py
multifib.egg-info/PKG-INFO
multifib.egg-info/SOURCES.txt
multifib.egg-info/dependency_links.txt
multifib.egg-info/top_level.txt