Metadata-Version: 1.0
Name: multifib
Version: 0.1
Summary: Multiple Fibonacci Number Implementations, in Python and C
Home-page: UNKNOWN
Author: Dan Crosta
Author-email: dcrosta@late.am
License: BSD
Platform: UNKNOWN
